jwkaas/__init__.py
jwkaas/algorithms.py
jwkaas/compat.py
jwkaas/jwkaas.py
jwkaas/utils.py
jwkaas-1.0.1.dist-info/LICENSE
jwkaas-1.0.1.dist-info/METADATA
jwkaas-1.0.1.dist-info/WHEEL
jwkaas-1.0.1.dist-info/top_level.txt
jwkaas-1.0.1.dist-info/RECORD
