Metadata-Version: 2.1
Name: jwkaas
Version: 1.0.1
Summary: JSON Web Key Advanced Acquiring Store
Home-page: https://github.com/vwt-digital/jwkaas
Author: Bernie van Veen
Author-email: b.vanveen@vwt.digital
License: gpl-3.0
Platform: UNKNOWN
Classifier: Programming Language :: Python :: 3
Classifier: License :: OSI Approved :: GNU General Public License v3 (GPLv3)
Classifier: Operating System :: OS Independent
Requires-Python: >=3.6
Requires-Dist: PyJWT (==2.1.0)
Requires-Dist: certifi (==2021.5.30)
Requires-Dist: cffi (==1.14.5)
Requires-Dist: chardet (==4.0.0)
Requires-Dist: cryptography (==3.4.7)
Requires-Dist: idna (==2.10)
Requires-Dist: pycparser (==2.20)
Requires-Dist: requests (==2.25.1)
Requires-Dist: urllib3 (==1.26.5)
